{
    "name": "MoonlitJolteon",
    "avatarSource": "https://www.vrmasterleague.com//images/logos/users/35da6bcc-ac42-44a4-8560-27ecc4a4a091.png",
    "teamExists": true,
    "logoSource": "https://www.vrmasterleague.com//images/logos/teams/262c0846-9f88-4472-ad9e-f038c214442a.png",
    "teamName": "Nani Reforged",
    "score": {
        "mmr": true,
        "score": "1100"
    },
    "teamWL": "5-0-7",
    "username": "MoonlitJolteon",
    "division": "https://www.vrmasterleague.com//images/div_silver_1_40.png",
    "panel": "style=\"background: #b3b3b3d1 !important;\"",
    "background": "style=\"border-color: #b3b3b3 !important; background-color: #444444 !important;\"",
    "country": "us",
    "playerStats": {
        "Level": "50",
        "Goals": "302",
        "Points": "723",
        "2 Pointers": "209",
        "3 Pointers": "93",
        "Estimated Height": "1.84 m (6' 0\")",
        "Dominant Hand": "Right (16% left handed)",
        "Plays Inverted": " Non-Inverted(2% inverted)",
        "Play Time": "26.2 hr",
        "Games": "319",
        "Wins": "182",
        "Assists": "152",
        "Shots Taken": "685",
        "Saves": "182",
        "Stuns": "2913",
        "Steals": "258",
        "Possesion Time": "4.4 hr",
        "Late Joins": "None",
        "Early Quits": "None",
        "Win Rate": "57.05%",
        "Win Rate (Last 50 Games)": "66%",
        "Goal Percentage": "44.1%",
        "Goal Avg": "0.95",
        "Point Avg": "2.27",
        "Shot Attempts Avg": "2.15",
        "Save Avg": "0.57",
        "Stun Avg": "9.13",
        "Steal Avg": "0.81",
        "Assist Avg": "0.48",
        "3-Pointer Ratio": "31%",
        "Avg Speed": "4.9 m/s",
        "Avg Throw Speed": "9.4 m/s",
        "Backboard Rate": "71.9%",
        "Avg Goal Speed": "13.0 m/s",
        "Avg Goal Angle": "38.5°",
        "Avg Goal Distance": "6.5 m"
    }
}